sider_ai_api
