Metadata-Version: 2.1
Name: sider-ai-api
Version: 1.0.1
Summary: An API library for sider.ai, providing alternative access to ChatGPT, Gemini, Claude, and other models. 国内访问ChatGPT、Gemini、Claude的替代解决方案，访问sider.ai的API请求库。
Home-page: https://github.com/qfcy/sider-ai-api
Author: qfcy
Author-email: 3076711200@qq.com
Keywords: sider.ai,chatgpt,gemini,claude,llama,o1,deepseek,深度求索
Classifier: Programming Language :: Python
Classifier: Topic :: Scientific/Engineering :: Artificial Intelligence
Classifier: Topic :: Internet :: WWW/HTTP
